localblast/__init__.py
localblast/_binaries.py
localblast/_platform.py
localblast/core.py
localblast/parsers/__init__.py
localblast/wrappers/__init__.py
localblast/wrappers/makeblastdb.py
localblast-0.1.0.dist-info/METADATA
localblast-0.1.0.dist-info/WHEEL
localblast-0.1.0.dist-info/RECORD
