Metadata-Version: 2.4
Name: localblast
Version: 0.1.0
Summary: NCBI BLAST+ wrapper with automatic binary downloading and caching.
Requires-Python: >=3.10
Requires-Dist: biopython>=1.83
